src/__init__.py
src/auto_eda.py
auto_eda-0.1.8.dist-info/LICENSE
auto_eda-0.1.8.dist-info/METADATA
auto_eda-0.1.8.dist-info/WHEEL
auto_eda-0.1.8.dist-info/entry_points.txt
auto_eda-0.1.8.dist-info/top_level.txt
auto_eda-0.1.8.dist-info/RECORD
