Metadata-Version: 2.1
Name: auto-eda
Version: 0.1.8
Summary: It is an automatic script that generating information in the dataset.
Home-page: https://github.com/jinisaweaklearner/auto-eda
Author: Jin Xiaocheng
Author-email: xiaochengjin.random@gmail.com
License: MIT
Keywords: python package auto eda
Platform: UNKNOWN
Classifier: Programming Language :: Python :: 3
Classifier: License :: OSI Approved :: MIT License
Classifier: Operating System :: OS Independent
Requires-Dist: pandas (==0.25.3)
Requires-Dist: numpy (==1.17.4)
